kcho/__init__.py
kcho/collocation.py
kcho/create_gold_standard.py
kcho/eng_kcho_parallel_extractor.py
kcho/evaluation.py
kcho/export.py
kcho/export_training_csv.py
kcho/kcho_app.py
kcho/kcho_system.py
kcho/normalize.py
kcho/data/linguistic_data.json
kcho/data/word_frequency_top_1000.csv
kcho_linguistic_toolkit-0.1.0.dist-info/licenses/LICENSE
kcho_linguistic_toolkit-0.1.0.dist-info/METADATA
kcho_linguistic_toolkit-0.1.0.dist-info/WHEEL
kcho_linguistic_toolkit-0.1.0.dist-info/entry_points.txt
kcho_linguistic_toolkit-0.1.0.dist-info/top_level.txt
kcho_linguistic_toolkit-0.1.0.dist-info/RECORD
