Metadata-Version: 2.4
Name: kcho-linguistic-toolkit
Version: 0.1.0
Summary: K'Cho linguistic analysis toolkit for low-resource NLP with collocation extraction, morphological analysis, and corpus processing
Author-email: Hung Om <hungom@example.com>
License: MIT
Project-URL: Homepage, https://github.com/HungOm/kcho-linguistic-toolkit
Project-URL: Documentation, https://github.com/HungOm/kcho-linguistic-toolkit#readme
Project-URL: Repository, https://github.com/HungOm/kcho-linguistic-toolkit
Project-URL: Issues, https://github.com/HungOm/kcho-linguistic-toolkit/issues
Keywords: nlp,low-resource,kcho,linguistics,collocation,morphology,corpus,language-processing
Classifier: Development Status :: 4 - Beta
Classifier: Intended Audience :: Science/Research
Classifier: Intended Audience :: Developers
Classifier: License :: OSI Approved :: MIT License
Classifier: Programming Language :: Python :: 3
Classifier: Programming Language :: Python :: 3.8
Classifier: Programming Language :: Python :: 3.9
Classifier: Programming Language :: Python :: 3.10
Classifier: Programming Language :: Python :: 3.11
Classifier: Programming Language :: Python :: 3.12
Classifier: Topic :: Scientific/Engineering :: Artificial Intelligence
Classifier: Topic :: Text Processing :: Linguistic
Classifier: Topic :: Scientific/Engineering :: Information Analysis
Requires-Python: >=3.8
License-File: LICENSE
Requires-Dist: nltk>=3.7
Requires-Dist: scikit-learn>=1.0
Requires-Dist: click>=8.0
Requires-Dist: numpy>=1.20
Provides-Extra: dev
Requires-Dist: pytest>=7.0; extra == "dev"
Requires-Dist: black>=22.0; extra == "dev"
Requires-Dist: flake8>=4.0; extra == "dev"
Dynamic: license-file
